topsis/__init__.py
topsis/topsis.py
topsis_agamdeep_555-0.1.6.dist-info/METADATA
topsis_agamdeep_555-0.1.6.dist-info/WHEEL
topsis_agamdeep_555-0.1.6.dist-info/top_level.txt
topsis_agamdeep_555-0.1.6.dist-info/RECORD
