Metadata-Version: 2.4
Name: topsis-agamdeep-555
Version: 0.1.6
Summary: Short description of my project
Author: Agamdeep Singh
Author-email: Agamdeep Singh <agamdeepsingh555@gmail.com>
License: MIT
Requires-Python: >=3.8
Dynamic: author
